[
{
	"camera_info" : 
	{
		"encoding" : "h264",
		"firmware_version" : "V5.7.3 build 211009",
		"id" : "88",
		"manufacturer" : "HIKVISION",
		"model" : "DS-2DF8C442IXS-AELW",
		"num_configurations" : 3,
		"serial_num" : "DS-2DF8C442IXS-AELW20220514CCWRJ64027709"
	}
},
{
	"time_ns" : 1705575013986896344,
	"trackable" : 0
},
{
	"time_ns" : 1705575014026985532,
	"trackable" : 0
},
{
	"time_ns" : 1705575014066862551,
	"trackable" : 0
},
{
	"time_ns" : 1705575014107218019,
	"trackable" : 0
},
{
	"time_ns" : 1705575014147248149,
	"trackable" : 0
},
{
	"time_ns" : 1705575014187332097,
	"trackable" : 0
},
{
	"time_ns" : 1705575014227458209,
	"trackable" : 0
},
{
	"time_ns" : 1705575014267521830,
	"trackable" : 0
},
{
	"time_ns" : 1705575014307573932,
	"trackable" : 0
},
{
	"time_ns" : 1705575014347664144,
	"trackable" : 0
},
{
	"time_ns" : 1705575014387811840,
	"trackable" : 0
},
{
	"time_ns" : 1705575014427880480,
	"trackable" : 0
},
{
	"time_ns" : 1705575014467945751,
	"trackable" : 0
},
{
	"time_ns" : 1705575014508011199,
	"trackable" : 0
},
{
	"time_ns" : 1705575014547889953,
	"trackable" : 0
},
{
	"time_ns" : 1705575014588214361,
	"trackable" : 0
},
{
	"time_ns" : 1705575014628360527,
	"trackable" : 0
},
{
	"time_ns" : 1705575014668213919,
	"trackable" : 0
},
{
	"time_ns" : 1705575014708613450,
	"trackable" : 0
},
{
	"time_ns" : 1705575014748664640,
	"trackable" : 0
},
{
	"time_ns" : 1705575014788786926,
	"trackable" : 0
},
{
	"time_ns" : 1705575014829041902,
	"trackable" : 0
},
{
	"time_ns" : 1705575014868897403,
	"trackable" : 0
},
{
	"time_ns" : 1705575014908923888,
	"trackable" : 0
},
{
	"time_ns" : 1705575014949070470,
	"trackable" : 0
},
{
	"time_ns" : 1705575014989105040,
	"trackable" : 0
},
{
	"time_ns" : 1705575015029181140,
	"trackable" : 0
},
{
	"time_ns" : 1705575015069177756,
	"trackable" : 0
},
{
	"time_ns" : 1705575015109331990,
	"trackable" : 0
},
{
	"time_ns" : 1705575015149379805,
	"trackable" : 0
},
{
	"time_ns" : 1705575015189512225,
	"trackable" : 0
},
{
	"time_ns" : 1705575015229574263,
	"trackable" : 0
},
{
	"time_ns" : 1705575015269488015,
	"trackable" : 0
},
{
	"time_ns" : 1705575015309842960,
	"trackable" : 0
},
{
	"time_ns" : 1705575015349962550,
	"trackable" : 0
},
{
	"time_ns" : 1705575015389976247,
	"trackable" : 0
},
{
	"time_ns" : 1705575015430060486,
	"trackable" : 0
},
{
	"time_ns" : 1705575015470164300,
	"trackable" : 0
},
{
	"time_ns" : 1705575015510253005,
	"trackable" : 0
},
{
	"time_ns" : 1705575015550327469,
	"trackable" : 0
},
{
	"time_ns" : 1705575015590433551,
	"trackable" : 0
},
{
	"time_ns" : 1705575015630481730,
	"trackable" : 0
},
{
	"time_ns" : 1705575015670550770,
	"trackable" : 0
},
{
	"time_ns" : 1705575015710763140,
	"trackable" : 0
},
{
	"time_ns" : 1705575015750788723,
	"trackable" : 0
},
{
	"time_ns" : 1705575015790943544,
	"trackable" : 0
},
{
	"time_ns" : 1705575015830998495,
	"trackable" : 0
},
{
	"time_ns" : 1705575015870924686,
	"trackable" : 0
},
{
	"time_ns" : 1705575015911226046,
	"trackable" : 0
},
{
	"time_ns" : 1705575015951337236,
	"trackable" : 0
},
{
	"detections" : 
	[
		{
			"bbox" : 
			{
				"height" : 21.0,
				"width" : 17.0,
				"x" : 29.0,
				"y" : 1039.0
			},
			"id" : 107,
			"state" : 2
		}
	],
	"time_ns" : 1705575016112247762,
	"trackable" : 1
},
{
	"detections" : 
	[
		{
			"bbox" : 
			{
				"height" : 22.0,
				"width" : 18.0,
				"x" : 40.0,
				"y" : 1043.0
			},
			"id" : 107,
			"state" : 2
		}
	],
	"time_ns" : 1705575016152617719,
	"trackable" : 1
},
{
	"detections" : 
	[
		{
			"bbox" : 
			{
				"height" : 21.0,
				"width" : 17.0,
				"x" : 48.0,
				"y" : 1046.0
			},
			"id" : 107,
			"state" : 2
		}
	],
	"time_ns" : 1705575016191670794,
	"trackable" : 1
},
{
	"detections" : 
	[
		{
			"bbox" : 
			{
				"height" : 22.0,
				"width" : 18.0,
				"x" : 57.0,
				"y" : 1048.0
			},
			"id" : 107,
			"state" : 2
		}
	],
	"time_ns" : 1705575016231758832,
	"trackable" : 1
},
{
	"detections" : 
	[
		{
			"bbox" : 
			{
				"height" : 23.0,
				"width" : 18.0,
				"x" : 65.0,
				"y" : 1050.0
			},
			"id" : 107,
			"state" : 2
		}
	],
	"time_ns" : 1705575016272726746,
	"trackable" : 1
},
{
	"detections" : 
	[
		{
			"bbox" : 
			{
				"height" : 21.0,
				"width" : 17.0,
				"x" : 72.0,
				"y" : 1053.0
			},
			"id" : 107,
			"state" : 2
		}
	],
	"time_ns" : 1705575016312798623,
	"trackable" : 1
},
{
	"detections" : 
	[
		{
			"bbox" : 
			{
				"height" : 20.0,
				"width" : 17.0,
				"x" : 81.0,
				"y" : 1055.0
			},
			"id" : 107,
			"state" : 2
		}
	],
	"time_ns" : 1705575016352961073,
	"trackable" : 1
},
{
	"detections" : 
	[
		{
			"bbox" : 
			{
				"height" : 22.0,
				"width" : 17.0,
				"x" : 90.0,
				"y" : 1057.0
			},
			"id" : 107,
			"state" : 2
		}
	],
	"time_ns" : 1705575016392608441,
	"trackable" : 1
},
{
	"detections" : 
	[
		{
			"bbox" : 
			{
				"height" : 20.0,
				"width" : 18.0,
				"x" : 99.0,
				"y" : 1060.0
			},
			"id" : 107,
			"state" : 2
		}
	],
	"time_ns" : 1705575016433024039,
	"trackable" : 1
},
{
	"detections" : 
	[
		{
			"bbox" : 
			{
				"height" : 19.0,
				"width" : 17.0,
				"x" : 107.0,
				"y" : 1062.0
			},
			"id" : 107,
			"state" : 2
		}
	],
	"time_ns" : 1705575016473434141,
	"trackable" : 1
},
{
	"detections" : 
	[
		{
			"bbox" : 
			{
				"height" : 19.0,
				"width" : 18.0,
				"x" : 116.0,
				"y" : 1063.0
			},
			"id" : 107,
			"state" : 2
		}
	],
	"time_ns" : 1705575016519105758,
	"trackable" : 1
},
{
	"detections" : 
	[
		{
			"bbox" : 
			{
				"height" : 20.0,
				"width" : 19.0,
				"x" : 125.0,
				"y" : 1066.0
			},
			"id" : 107,
			"state" : 2
		}
	],
	"time_ns" : 1705575016556803144,
	"trackable" : 1
},
{
	"detections" : 
	[
		{
			"bbox" : 
			{
				"height" : 19.0,
				"width" : 17.0,
				"x" : 134.0,
				"y" : 1067.0
			},
			"id" : 107,
			"state" : 2
		}
	],
	"time_ns" : 1705575016595907454,
	"trackable" : 1
},
{
	"detections" : 
	[
		{
			"bbox" : 
			{
				"height" : 19.0,
				"width" : 20.0,
				"x" : 141.0,
				"y" : 1069.0
			},
			"id" : 107,
			"state" : 2
		}
	],
	"time_ns" : 1705575016636489569,
	"trackable" : 1
},
{
	"detections" : 
	[
		{
			"bbox" : 
			{
				"height" : 19.0,
				"width" : 16.0,
				"x" : 152.0,
				"y" : 1071.0
			},
			"id" : 107,
			"state" : 2
		}
	],
	"time_ns" : 1705575016675853546,
	"trackable" : 1
},
{
	"detections" : 
	[
		{
			"bbox" : 
			{
				"height" : 20.0,
				"width" : 16.0,
				"x" : 161.0,
				"y" : 1074.0
			},
			"id" : 107,
			"state" : 2
		}
	],
	"time_ns" : 1705575016714526529,
	"trackable" : 1
},
{
	"detections" : 
	[
		{
			"bbox" : 
			{
				"height" : 20.0,
				"width" : 17.0,
				"x" : 170.0,
				"y" : 1075.0
			},
			"id" : 107,
			"state" : 2
		}
	],
	"time_ns" : 1705575016754739043,
	"trackable" : 1
},
{
	"detections" : 
	[
		{
			"bbox" : 
			{
				"height" : 20.0,
				"width" : 16.0,
				"x" : 180.0,
				"y" : 1077.0
			},
			"id" : 107,
			"state" : 2
		}
	],
	"time_ns" : 1705575016797331788,
	"trackable" : 1
},
{
	"detections" : 
	[
		{
			"bbox" : 
			{
				"height" : 18.0,
				"width" : 16.0,
				"x" : 189.0,
				"y" : 1078.0
			},
			"id" : 107,
			"state" : 2
		}
	],
	"time_ns" : 1705575016838089309,
	"trackable" : 1
},
{
	"detections" : 
	[
		{
			"bbox" : 
			{
				"height" : 19.0,
				"width" : 17.0,
				"x" : 198.0,
				"y" : 1079.0
			},
			"id" : 107,
			"state" : 2
		}
	],
	"time_ns" : 1705575016879426023,
	"trackable" : 1
},
{
	"detections" : 
	[
		{
			"bbox" : 
			{
				"height" : 20.0,
				"width" : 17.0,
				"x" : 207.0,
				"y" : 1080.0
			},
			"id" : 107,
			"state" : 2
		}
	],
	"time_ns" : 1705575016919869708,
	"trackable" : 1
},
{
	"detections" : 
	[
		{
			"bbox" : 
			{
				"height" : 20.0,
				"width" : 16.0,
				"x" : 217.0,
				"y" : 1082.0
			},
			"id" : 107,
			"state" : 2
		}
	],
	"time_ns" : 1705575016959948112,
	"trackable" : 1
},
{
	"detections" : 
	[
		{
			"bbox" : 
			{
				"height" : 20.0,
				"width" : 15.0,
				"x" : 225.0,
				"y" : 1083.0
			},
			"id" : 107,
			"state" : 2
		}
	],
	"time_ns" : 1705575017001179979,
	"trackable" : 1
},
{
	"detections" : 
	[
		{
			"bbox" : 
			{
				"height" : 20.0,
				"width" : 15.0,
				"x" : 236.0,
				"y" : 1084.0
			},
			"id" : 107,
			"state" : 2
		}
	],
	"time_ns" : 1705575017042695255,
	"trackable" : 1
},
{
	"detections" : 
	[
		{
			"bbox" : 
			{
				"height" : 18.0,
				"width" : 15.0,
				"x" : 245.0,
				"y" : 1085.0
			},
			"id" : 107,
			"state" : 2
		}
	],
	"time_ns" : 1705575017081282218,
	"trackable" : 1
},
{
	"detections" : 
	[
		{
			"bbox" : 
			{
				"height" : 19.0,
				"width" : 14.0,
				"x" : 255.0,
				"y" : 1086.0
			},
			"id" : 107,
			"state" : 2
		}
	],
	"time_ns" : 1705575017121699339,
	"trackable" : 1
},
{
	"detections" : 
	[
		{
			"bbox" : 
			{
				"height" : 18.0,
				"width" : 14.0,
				"x" : 264.0,
				"y" : 1088.0
			},
			"id" : 107,
			"state" : 2
		}
	],
	"time_ns" : 1705575017162374195,
	"trackable" : 1
},
{
	"detections" : 
	[
		{
			"bbox" : 
			{
				"height" : 19.0,
				"width" : 13.0,
				"x" : 275.0,
				"y" : 1088.0
			},
			"id" : 107,
			"state" : 2
		}
	],
	"time_ns" : 1705575017201873239,
	"trackable" : 1
},
{
	"detections" : 
	[
		{
			"bbox" : 
			{
				"height" : 19.0,
				"width" : 17.0,
				"x" : 282.0,
				"y" : 1089.0
			},
			"id" : 107,
			"state" : 2
		}
	],
	"time_ns" : 1705575017238346943,
	"trackable" : 1
},
{
	"detections" : 
	[
		{
			"bbox" : 
			{
				"height" : 20.0,
				"width" : 15.0,
				"x" : 291.0,
				"y" : 1090.0
			},
			"id" : 107,
			"state" : 2
		}
	],
	"time_ns" : 1705575017278434465,
	"trackable" : 1
},
{
	"detections" : 
	[
		{
			"bbox" : 
			{
				"height" : 20.0,
				"width" : 11.0,
				"x" : 301.0,
				"y" : 1091.0
			},
			"id" : 107,
			"state" : 2
		}
	],
	"time_ns" : 1705575017319240101,
	"trackable" : 1
},
{
	"detections" : 
	[
		{
			"bbox" : 
			{
				"height" : 19.0,
				"width" : 10.0,
				"x" : 311.0,
				"y" : 1092.0
			},
			"id" : 107,
			"state" : 2
		}
	],
	"time_ns" : 1705575017359416177,
	"trackable" : 1
},
{
	"detections" : 
	[
		{
			"bbox" : 
			{
				"height" : 18.0,
				"width" : 9.0,
				"x" : 319.0,
				"y" : 1093.0
			},
			"id" : 107,
			"state" : 2
		}
	],
	"time_ns" : 1705575017399210956,
	"trackable" : 1
},
{
	"detections" : 
	[
		{
			"bbox" : 
			{
				"height" : 19.0,
				"width" : 11.0,
				"x" : 328.0,
				"y" : 1093.0
			},
			"id" : 107,
			"state" : 2
		}
	],
	"time_ns" : 1705575017439229236,
	"trackable" : 1
},
{
	"detections" : 
	[
		{
			"bbox" : 
			{
				"height" : 20.0,
				"width" : 11.0,
				"x" : 338.0,
				"y" : 1095.0
			},
			"id" : 107,
			"state" : 2
		}
	],
	"time_ns" : 1705575017478727740,
	"trackable" : 1
},
{
	"detections" : 
	[
		{
			"bbox" : 
			{
				"height" : 21.0,
				"width" : 11.0,
				"x" : 355.0,
				"y" : 1097.0
			},
			"id" : 107,
			"state" : 2
		}
	],
	"time_ns" : 1705575017559199856,
	"trackable" : 1
},
{
	"detections" : 
	[
		{
			"bbox" : 
			{
				"height" : 21.0,
				"width" : 11.0,
				"x" : 372.0,
				"y" : 1097.0
			},
			"id" : 107,
			"state" : 2
		}
	],
	"time_ns" : 1705575017639523224,
	"trackable" : 1
},
{
	"detections" : 
	[
		{
			"bbox" : 
			{
				"height" : 20.0,
				"width" : 13.0,
				"x" : 380.0,
				"y" : 1099.0
			},
			"id" : 107,
			"state" : 2
		}
	],
	"time_ns" : 1705575017679987252,
	"trackable" : 1
},
{
	"detections" : 
	[
		{
			"bbox" : 
			{
				"height" : 20.0,
				"width" : 12.0,
				"x" : 389.0,
				"y" : 1100.0
			},
			"id" : 107,
			"state" : 2
		}
	],
	"time_ns" : 1705575017719176732,
	"trackable" : 1
},
{
	"detections" : 
	[
		{
			"bbox" : 
			{
				"height" : 21.0,
				"width" : 10.0,
				"x" : 399.0,
				"y" : 1100.0
			},
			"id" : 107,
			"state" : 2
		}
	],
	"time_ns" : 1705575017760782073,
	"trackable" : 1
},
{
	"detections" : 
	[
		{
			"bbox" : 
			{
				"height" : 19.0,
				"width" : 11.0,
				"x" : 408.0,
				"y" : 1101.0
			},
			"id" : 107,
			"state" : 2
		}
	],
	"time_ns" : 1705575017800200908,
	"trackable" : 1
},
{
	"detections" : 
	[
		{
			"bbox" : 
			{
				"height" : 21.0,
				"width" : 11.0,
				"x" : 416.0,
				"y" : 1102.0
			},
			"id" : 107,
			"state" : 2
		}
	],
	"time_ns" : 1705575017840961365,
	"trackable" : 1
},
{
	"detections" : 
	[
		{
			"bbox" : 
			{
				"height" : 20.0,
				"width" : 10.0,
				"x" : 425.0,
				"y" : 1103.0
			},
			"id" : 107,
			"state" : 2
		}
	],
	"time_ns" : 1705575017879242207,
	"trackable" : 1
},
{
	"detections" : 
	[
		{
			"bbox" : 
			{
				"height" : 21.0,
				"width" : 11.0,
				"x" : 434.0,
				"y" : 1104.0
			},
			"id" : 107,
			"state" : 2
		}
	],
	"time_ns" : 1705575017918555615,
	"trackable" : 1
},
{
	"detections" : 
	[
		{
			"bbox" : 
			{
				"height" : 22.0,
				"width" : 10.0,
				"x" : 443.0,
				"y" : 1105.0
			},
			"id" : 107,
			"state" : 2
		}
	],
	"time_ns" : 1705575017958941105,
	"trackable" : 1
},
{
	"detections" : 
	[
		{
			"bbox" : 
			{
				"height" : 22.0,
				"width" : 10.0,
				"x" : 451.0,
				"y" : 1107.0
			},
			"id" : 107,
			"state" : 2
		}
	],
	"time_ns" : 1705575017998667177,
	"trackable" : 1
},
{
	"detections" : 
	[
		{
			"bbox" : 
			{
				"height" : 23.0,
				"width" : 10.0,
				"x" : 460.0,
				"y" : 1107.0
			},
			"id" : 107,
			"state" : 2
		}
	],
	"time_ns" : 1705575018038958372,
	"trackable" : 1
},
{
	"detections" : 
	[
		{
			"bbox" : 
			{
				"height" : 24.0,
				"width" : 10.0,
				"x" : 468.0,
				"y" : 1109.0
			},
			"id" : 107,
			"state" : 2
		}
	],
	"time_ns" : 1705575018079332284,
	"trackable" : 1
},
{
	"detections" : 
	[
		{
			"bbox" : 
			{
				"height" : 22.0,
				"width" : 11.0,
				"x" : 477.0,
				"y" : 1110.0
			},
			"id" : 107,
			"state" : 2
		}
	],
	"time_ns" : 1705575018119153568,
	"trackable" : 1
},
{
	"detections" : 
	[
		{
			"bbox" : 
			{
				"height" : 22.0,
				"width" : 11.0,
				"x" : 486.0,
				"y" : 1111.0
			},
			"id" : 107,
			"state" : 2
		}
	],
	"time_ns" : 1705575018158926852,
	"trackable" : 1
},
{
	"detections" : 
	[
		{
			"bbox" : 
			{
				"height" : 23.0,
				"width" : 11.0,
				"x" : 494.0,
				"y" : 1112.0
			},
			"id" : 107,
			"state" : 2
		}
	],
	"time_ns" : 1705575018198934894,
	"trackable" : 1
},
{
	"detections" : 
	[
		{
			"bbox" : 
			{
				"height" : 24.0,
				"width" : 11.0,
				"x" : 503.0,
				"y" : 1113.0
			},
			"id" : 107,
			"state" : 2
		}
	],
	"time_ns" : 1705575018239711472,
	"trackable" : 1
},
{
	"detections" : 
	[
		{
			"bbox" : 
			{
				"height" : 24.0,
				"width" : 15.0,
				"x" : 509.0,
				"y" : 1114.0
			},
			"id" : 107,
			"state" : 2
		}
	],
	"time_ns" : 1705575018279046115,
	"trackable" : 1
},
{
	"detections" : 
	[
		{
			"bbox" : 
			{
				"height" : 25.0,
				"width" : 12.0,
				"x" : 519.0,
				"y" : 1116.0
			},
			"id" : 107,
			"state" : 2
		}
	],
	"time_ns" : 1705575018319371730,
	"trackable" : 1
},
{
	"detections" : 
	[
		{
			"bbox" : 
			{
				"height" : 25.0,
				"width" : 12.0,
				"x" : 529.0,
				"y" : 1116.0
			},
			"id" : 107,
			"state" : 2
		}
	],
	"time_ns" : 1705575018359208621,
	"trackable" : 1
},
{
	"detections" : 
	[
		{
			"bbox" : 
			{
				"height" : 26.0,
				"width" : 11.0,
				"x" : 538.0,
				"y" : 1118.0
			},
			"id" : 107,
			"state" : 2
		}
	],
	"time_ns" : 1705575018399431518,
	"trackable" : 1
},
{
	"detections" : 
	[
		{
			"bbox" : 
			{
				"height" : 24.0,
				"width" : 12.0,
				"x" : 546.0,
				"y" : 1120.0
			},
			"id" : 107,
			"state" : 2
		}
	],
	"time_ns" : 1705575018442288664,
	"trackable" : 1
},
{
	"detections" : 
	[
		{
			"bbox" : 
			{
				"height" : 26.0,
				"width" : 10.0,
				"x" : 555.0,
				"y" : 1121.0
			},
			"id" : 107,
			"state" : 2
		}
	],
	"time_ns" : 1705575018482022941,
	"trackable" : 1
},
{
	"detections" : 
	[
		{
			"bbox" : 
			{
				"height" : 25.0,
				"width" : 11.0,
				"x" : 565.0,
				"y" : 1122.0
			},
			"id" : 107,
			"state" : 2
		}
	],
	"time_ns" : 1705575018521163525,
	"trackable" : 1
},
{
	"detections" : 
	[
		{
			"bbox" : 
			{
				"height" : 25.0,
				"width" : 13.0,
				"x" : 572.0,
				"y" : 1123.0
			},
			"id" : 107,
			"state" : 2
		}
	],
	"time_ns" : 1705575018563284625,
	"trackable" : 1
},
{
	"detections" : 
	[
		{
			"bbox" : 
			{
				"height" : 25.0,
				"width" : 15.0,
				"x" : 579.0,
				"y" : 1124.0
			},
			"id" : 107,
			"state" : 2
		}
	],
	"time_ns" : 1705575018601883513,
	"trackable" : 1
},
{
	"detections" : 
	[
		{
			"bbox" : 
			{
				"height" : 26.0,
				"width" : 16.0,
				"x" : 588.0,
				"y" : 1127.0
			},
			"id" : 107,
			"state" : 2
		}
	],
	"time_ns" : 1705575018641149811,
	"trackable" : 1
},
{
	"detections" : 
	[
		{
			"bbox" : 
			{
				"height" : 26.0,
				"width" : 16.0,
				"x" : 597.0,
				"y" : 1127.0
			},
			"id" : 107,
			"state" : 2
		}
	],
	"time_ns" : 1705575018681858316,
	"trackable" : 1
},
{
	"detections" : 
	[
		{
			"bbox" : 
			{
				"height" : 25.0,
				"width" : 16.0,
				"x" : 606.0,
				"y" : 1128.0
			},
			"id" : 107,
			"state" : 2
		}
	],
	"time_ns" : 1705575018723380271,
	"trackable" : 1
},
{
	"detections" : 
	[
		{
			"bbox" : 
			{
				"height" : 25.0,
				"width" : 17.0,
				"x" : 614.0,
				"y" : 1129.0
			},
			"id" : 107,
			"state" : 2
		}
	],
	"time_ns" : 1705575018762087090,
	"trackable" : 1
},
{
	"detections" : 
	[
		{
			"bbox" : 
			{
				"height" : 26.0,
				"width" : 18.0,
				"x" : 623.0,
				"y" : 1131.0
			},
			"id" : 107,
			"state" : 2
		}
	],
	"time_ns" : 1705575018801825991,
	"trackable" : 1
},
{
	"detections" : 
	[
		{
			"bbox" : 
			{
				"height" : 27.0,
				"width" : 18.0,
				"x" : 639.0,
				"y" : 1132.0
			},
			"id" : 107,
			"state" : 2
		}
	],
	"time_ns" : 1705575018882098539,
	"trackable" : 1
},
{
	"detections" : 
	[
		{
			"bbox" : 
			{
				"height" : 26.0,
				"width" : 19.0,
				"x" : 650.0,
				"y" : 1134.0
			},
			"id" : 107,
			"state" : 2
		}
	],
	"time_ns" : 1705575018922934025,
	"trackable" : 1
},
{
	"detections" : 
	[
		{
			"bbox" : 
			{
				"height" : 25.0,
				"width" : 16.0,
				"x" : 661.0,
				"y" : 1135.0
			},
			"id" : 107,
			"state" : 2
		}
	],
	"time_ns" : 1705575018962174625,
	"trackable" : 1
},
{
	"detections" : 
	[
		{
			"bbox" : 
			{
				"height" : 25.0,
				"width" : 16.0,
				"x" : 670.0,
				"y" : 1136.0
			},
			"id" : 107,
			"state" : 2
		}
	],
	"time_ns" : 1705575019003096263,
	"trackable" : 1
},
{
	"detections" : 
	[
		{
			"bbox" : 
			{
				"height" : 25.0,
				"width" : 16.0,
				"x" : 680.0,
				"y" : 1137.0
			},
			"id" : 107,
			"state" : 2
		}
	],
	"time_ns" : 1705575019042422621,
	"trackable" : 1
},
{
	"detections" : 
	[
		{
			"bbox" : 
			{
				"height" : 23.0,
				"width" : 16.0,
				"x" : 688.0,
				"y" : 1139.0
			},
			"id" : 107,
			"state" : 2
		}
	],
	"time_ns" : 1705575019083844127,
	"trackable" : 1
},
{
	"detections" : 
	[
		{
			"bbox" : 
			{
				"height" : 24.0,
				"width" : 16.0,
				"x" : 698.0,
				"y" : 1140.0
			},
			"id" : 107,
			"state" : 2
		}
	],
	"time_ns" : 1705575019123791355,
	"trackable" : 1
},
{
	"detections" : 
	[
		{
			"bbox" : 
			{
				"height" : 23.0,
				"width" : 16.0,
				"x" : 707.0,
				"y" : 1141.0
			},
			"id" : 107,
			"state" : 2
		}
	],
	"time_ns" : 1705575019162282981,
	"trackable" : 1
},
{
	"detections" : 
	[
		{
			"bbox" : 
			{
				"height" : 24.0,
				"width" : 15.0,
				"x" : 715.0,
				"y" : 1143.0
			},
			"id" : 107,
			"state" : 2
		}
	],
	"time_ns" : 1705575019203008456,
	"trackable" : 1
},
{
	"detections" : 
	[
		{
			"bbox" : 
			{
				"height" : 25.0,
				"width" : 17.0,
				"x" : 723.0,
				"y" : 1144.0
			},
			"id" : 107,
			"state" : 2
		}
	],
	"time_ns" : 1705575019241991891,
	"trackable" : 1
},
{
	"detections" : 
	[
		{
			"bbox" : 
			{
				"height" : 25.0,
				"width" : 17.0,
				"x" : 733.0,
				"y" : 1145.0
			},
			"id" : 107,
			"state" : 2
		}
	],
	"time_ns" : 1705575019291033831,
	"trackable" : 1
},
{
	"detections" : 
	[
		{
			"bbox" : 
			{
				"height" : 26.0,
				"width" : 17.0,
				"x" : 742.0,
				"y" : 1147.0
			},
			"id" : 107,
			"state" : 2
		}
	],
	"time_ns" : 1705575019335239846,
	"trackable" : 1
},
{
	"detections" : 
	[
		{
			"bbox" : 
			{
				"height" : 25.0,
				"width" : 17.0,
				"x" : 751.0,
				"y" : 1148.0
			},
			"id" : 107,
			"state" : 2
		}
	],
	"time_ns" : 1705575019365206750,
	"trackable" : 1
},
{
	"detections" : 
	[
		{
			"bbox" : 
			{
				"height" : 25.0,
				"width" : 17.0,
				"x" : 760.0,
				"y" : 1149.0
			},
			"id" : 107,
			"state" : 2
		}
	],
	"time_ns" : 1705575019403946681,
	"trackable" : 1
},
{
	"detections" : 
	[
		{
			"bbox" : 
			{
				"height" : 25.0,
				"width" : 15.0,
				"x" : 769.0,
				"y" : 1151.0
			},
			"id" : 107,
			"state" : 2
		}
	],
	"time_ns" : 1705575019444214492,
	"trackable" : 1
},
{
	"detections" : 
	[
		{
			"bbox" : 
			{
				"height" : 27.0,
				"width" : 19.0,
				"x" : 777.0,
				"y" : 1153.0
			},
			"id" : 107,
			"state" : 2
		}
	],
	"time_ns" : 1705575019484221431,
	"trackable" : 1
},
{
	"detections" : 
	[
		{
			"bbox" : 
			{
				"height" : 27.0,
				"width" : 18.0,
				"x" : 787.0,
				"y" : 1154.0
			},
			"id" : 107,
			"state" : 2
		}
	],
	"time_ns" : 1705575019524410605,
	"trackable" : 1
},
{
	"detections" : 
	[
		{
			"bbox" : 
			{
				"height" : 28.0,
				"width" : 21.0,
				"x" : 795.0,
				"y" : 1156.0
			},
			"id" : 107,
			"state" : 2
		}
	],
	"time_ns" : 1705575019564439458,
	"trackable" : 1
},
{
	"detections" : 
	[
		{
			"bbox" : 
			{
				"height" : 26.0,
				"width" : 18.0,
				"x" : 804.0,
				"y" : 1159.0
			},
			"id" : 107,
			"state" : 2
		}
	],
	"time_ns" : 1705575019603810504,
	"trackable" : 1
},
{
	"detections" : 
	[
		{
			"bbox" : 
			{
				"height" : 27.0,
				"width" : 18.0,
				"x" : 812.0,
				"y" : 1160.0
			},
			"id" : 107,
			"state" : 2
		}
	],
	"time_ns" : 1705575019645019428,
	"trackable" : 1
},
{
	"detections" : 
	[
		{
			"bbox" : 
			{
				"height" : 27.0,
				"width" : 18.0,
				"x" : 822.0,
				"y" : 1162.0
			},
			"id" : 107,
			"state" : 2
		}
	],
	"time_ns" : 1705575019683699602,
	"trackable" : 1
},
{
	"detections" : 
	[
		{
			"bbox" : 
			{
				"height" : 26.0,
				"width" : 19.0,
				"x" : 829.0,
				"y" : 1164.0
			},
			"id" : 107,
			"state" : 2
		}
	],
	"time_ns" : 1705575019723594558,
	"trackable" : 1
},
{
	"detections" : 
	[
		{
			"bbox" : 
			{
				"height" : 26.0,
				"width" : 19.0,
				"x" : 839.0,
				"y" : 1166.0
			},
			"id" : 107,
			"state" : 2
		}
	],
	"time_ns" : 1705575019763772304,
	"trackable" : 1
},
{
	"detections" : 
	[
		{
			"bbox" : 
			{
				"height" : 25.0,
				"width" : 19.0,
				"x" : 848.0,
				"y" : 1169.0
			},
			"id" : 107,
			"state" : 2
		}
	],
	"time_ns" : 1705575019804904606,
	"trackable" : 1
},
{
	"detections" : 
	[
		{
			"bbox" : 
			{
				"height" : 25.0,
				"width" : 18.0,
				"x" : 858.0,
				"y" : 1170.0
			},
			"id" : 107,
			"state" : 2
		}
	],
	"time_ns" : 1705575019843631637,
	"trackable" : 1
},
{
	"detections" : 
	[
		{
			"bbox" : 
			{
				"height" : 23.0,
				"width" : 17.0,
				"x" : 865.0,
				"y" : 1173.0
			},
			"id" : 107,
			"state" : 2
		}
	],
	"time_ns" : 1705575019883882754,
	"trackable" : 1
},
{
	"detections" : 
	[
		{
			"bbox" : 
			{
				"height" : 24.0,
				"width" : 18.0,
				"x" : 874.0,
				"y" : 1175.0
			},
			"id" : 107,
			"state" : 2
		}
	],
	"time_ns" : 1705575019925396009,
	"trackable" : 1
},
{
	"detections" : 
	[
		{
			"bbox" : 
			{
				"height" : 25.0,
				"width" : 18.0,
				"x" : 883.0,
				"y" : 1177.0
			},
			"id" : 107,
			"state" : 2
		}
	],
	"time_ns" : 1705575019964622614,
	"trackable" : 1
},
{
	"detections" : 
	[
		{
			"bbox" : 
			{
				"height" : 23.0,
				"width" : 20.0,
				"x" : 891.0,
				"y" : 1180.0
			},
			"id" : 107,
			"state" : 2
		}
	],
	"time_ns" : 1705575020006838647,
	"trackable" : 1
},
{
	"detections" : 
	[
		{
			"bbox" : 
			{
				"height" : 24.0,
				"width" : 21.0,
				"x" : 907.0,
				"y" : 1186.0
			},
			"id" : 107,
			"state" : 2
		}
	],
	"time_ns" : 1705575020090313612,
	"trackable" : 1
},
{
	"detections" : 
	[
		{
			"bbox" : 
			{
				"height" : 24.0,
				"width" : 21.0,
				"x" : 916.0,
				"y" : 1188.0
			},
			"id" : 107,
			"state" : 2
		}
	],
	"time_ns" : 1705575020131816510,
	"trackable" : 1
},
{
	"detections" : 
	[
		{
			"bbox" : 
			{
				"height" : 24.0,
				"width" : 21.0,
				"x" : 925.0,
				"y" : 1190.0
			},
			"id" : 107,
			"state" : 2
		}
	],
	"time_ns" : 1705575020167606979,
	"trackable" : 1
},
{
	"detections" : 
	[
		{
			"bbox" : 
			{
				"height" : 24.0,
				"width" : 18.0,
				"x" : 943.0,
				"y" : 1197.0
			},
			"id" : 107,
			"state" : 2
		}
	],
	"time_ns" : 1705575020248626217,
	"trackable" : 1
},
{
	"detections" : 
	[
		{
			"bbox" : 
			{
				"height" : 24.0,
				"width" : 20.0,
				"x" : 951.0,
				"y" : 1198.0
			},
			"id" : 107,
			"state" : 2
		}
	],
	"time_ns" : 1705575020288453048,
	"trackable" : 1
},
{
	"detections" : 
	[
		{
			"bbox" : 
			{
				"height" : 22.0,
				"width" : 22.0,
				"x" : 959.0,
				"y" : 1201.0
			},
			"id" : 107,
			"state" : 2
		}
	],
	"time_ns" : 1705575020327708983,
	"trackable" : 1
},
{
	"detections" : 
	[
		{
			"bbox" : 
			{
				"height" : 25.0,
				"width" : 21.0,
				"x" : 967.0,
				"y" : 1203.0
			},
			"id" : 107,
			"state" : 2
		}
	],
	"time_ns" : 1705575020367700932,
	"trackable" : 1
},
{
	"detections" : 
	[
		{
			"bbox" : 
			{
				"height" : 23.0,
				"width" : 19.0,
				"x" : 976.0,
				"y" : 1206.0
			},
			"id" : 107,
			"state" : 2
		}
	],
	"time_ns" : 1705575020409382557,
	"trackable" : 1
},
{
	"detections" : 
	[
		{
			"bbox" : 
			{
				"height" : 22.0,
				"width" : 19.0,
				"x" : 985.0,
				"y" : 1210.0
			},
			"id" : 107,
			"state" : 2
		}
	],
	"time_ns" : 1705575020448493252,
	"trackable" : 1
},
{
	"detections" : 
	[
		{
			"bbox" : 
			{
				"height" : 22.0,
				"width" : 20.0,
				"x" : 993.0,
				"y" : 1212.0
			},
			"id" : 107,
			"state" : 2
		}
	],
	"time_ns" : 1705575020488030750,
	"trackable" : 1
},
{
	"detections" : 
	[
		{
			"bbox" : 
			{
				"height" : 22.0,
				"width" : 19.0,
				"x" : 1002.0,
				"y" : 1215.0
			},
			"id" : 107,
			"state" : 2
		}
	],
	"time_ns" : 1705575020528842812,
	"trackable" : 1
},
{
	"detections" : 
	[
		{
			"bbox" : 
			{
				"height" : 20.0,
				"width" : 20.0,
				"x" : 1010.0,
				"y" : 1218.0
			},
			"id" : 107,
			"state" : 2
		}
	],
	"time_ns" : 1705575020568972669,
	"trackable" : 1
},
{
	"detections" : 
	[
		{
			"bbox" : 
			{
				"height" : 21.0,
				"width" : 19.0,
				"x" : 1019.0,
				"y" : 1220.0
			},
			"id" : 107,
			"state" : 2
		}
	],
	"time_ns" : 1705575020606856998,
	"trackable" : 1
},
{
	"detections" : 
	[
		{
			"bbox" : 
			{
				"height" : 20.0,
				"width" : 19.0,
				"x" : 1028.0,
				"y" : 1224.0
			},
			"id" : 107,
			"state" : 2
		}
	],
	"time_ns" : 1705575020648412605,
	"trackable" : 1
},
{
	"detections" : 
	[
		{
			"bbox" : 
			{
				"height" : 20.0,
				"width" : 21.0,
				"x" : 1035.0,
				"y" : 1227.0
			},
			"id" : 107,
			"state" : 2
		}
	],
	"time_ns" : 1705575020689054125,
	"trackable" : 1
},
{
	"detections" : 
	[
		{
			"bbox" : 
			{
				"height" : 20.0,
				"width" : 21.0,
				"x" : 1044.0,
				"y" : 1230.0
			},
			"id" : 107,
			"state" : 2
		}
	],
	"time_ns" : 1705575020727161857,
	"trackable" : 1
},
{
	"detections" : 
	[
		{
			"bbox" : 
			{
				"height" : 20.0,
				"width" : 21.0,
				"x" : 1052.0,
				"y" : 1233.0
			},
			"id" : 107,
			"state" : 2
		}
	],
	"time_ns" : 1705575020768786641,
	"trackable" : 1
},
{
	"detections" : 
	[
		{
			"bbox" : 
			{
				"height" : 21.0,
				"width" : 21.0,
				"x" : 1062.0,
				"y" : 1235.0
			},
			"id" : 107,
			"state" : 2
		}
	],
	"time_ns" : 1705575020809396974,
	"trackable" : 1
},
{
	"detections" : 
	[
		{
			"bbox" : 
			{
				"height" : 20.0,
				"width" : 21.0,
				"x" : 1070.0,
				"y" : 1239.0
			},
			"id" : 107,
			"state" : 2
		}
	],
	"time_ns" : 1705575020849703802,
	"trackable" : 1
},
{
	"detections" : 
	[
		{
			"bbox" : 
			{
				"height" : 20.0,
				"width" : 20.0,
				"x" : 1079.0,
				"y" : 1242.0
			},
			"id" : 107,
			"state" : 2
		}
	],
	"time_ns" : 1705575020888267651,
	"trackable" : 1
},
{
	"detections" : 
	[
		{
			"bbox" : 
			{
				"height" : 20.0,
				"width" : 21.0,
				"x" : 1087.0,
				"y" : 1245.0
			},
			"id" : 107,
			"state" : 2
		}
	],
	"time_ns" : 1705575020929210501,
	"trackable" : 1
},
{
	"detections" : 
	[
		{
			"bbox" : 
			{
				"height" : 20.0,
				"width" : 21.0,
				"x" : 1096.0,
				"y" : 1248.0
			},
			"id" : 107,
			"state" : 2
		}
	],
	"time_ns" : 1705575020968257490,
	"trackable" : 1
},
{
	"detections" : 
	[
		{
			"bbox" : 
			{
				"height" : 21.0,
				"width" : 21.0,
				"x" : 1104.0,
				"y" : 1249.0
			},
			"id" : 107,
			"state" : 2
		}
	],
	"time_ns" : 1705575021009192267,
	"trackable" : 1
},
{
	"detections" : 
	[
		{
			"bbox" : 
			{
				"height" : 20.0,
				"width" : 21.0,
				"x" : 1112.0,
				"y" : 1253.0
			},
			"id" : 107,
			"state" : 2
		}
	],
	"time_ns" : 1705575021050069443,
	"trackable" : 1
},
{
	"detections" : 
	[
		{
			"bbox" : 
			{
				"height" : 19.0,
				"width" : 22.0,
				"x" : 1122.0,
				"y" : 1255.0
			},
			"id" : 107,
			"state" : 2
		}
	],
	"time_ns" : 1705575021092255792,
	"trackable" : 1
},
{
	"detections" : 
	[
		{
			"bbox" : 
			{
				"height" : 20.0,
				"width" : 20.0,
				"x" : 1130.0,
				"y" : 1258.0
			},
			"id" : 107,
			"state" : 2
		}
	],
	"time_ns" : 1705575021133380511,
	"trackable" : 1
},
{
	"detections" : 
	[
		{
			"bbox" : 
			{
				"height" : 19.0,
				"width" : 18.0,
				"x" : 1137.0,
				"y" : 1260.0
			},
			"id" : 107,
			"state" : 2
		}
	],
	"time_ns" : 1705575021173161221,
	"trackable" : 1
},
{
	"detections" : 
	[
		{
			"bbox" : 
			{
				"height" : 21.0,
				"width" : 20.0,
				"x" : 1152.0,
				"y" : 1265.0
			},
			"id" : 107,
			"state" : 2
		}
	],
	"time_ns" : 1705575021253921898,
	"trackable" : 1
},
{
	"detections" : 
	[
		{
			"bbox" : 
			{
				"height" : 21.0,
				"width" : 20.0,
				"x" : 1163.0,
				"y" : 1269.0
			},
			"id" : 107,
			"state" : 2
		}
	],
	"time_ns" : 1705575021293702796,
	"trackable" : 1
},
{
	"detections" : 
	[
		{
			"bbox" : 
			{
				"height" : 21.0,
				"width" : 22.0,
				"x" : 1171.0,
				"y" : 1272.0
			},
			"id" : 107,
			"state" : 2
		}
	],
	"time_ns" : 1705575021335158633,
	"trackable" : 1
},
{
	"detections" : 
	[
		{
			"bbox" : 
			{
				"height" : 20.0,
				"width" : 20.0,
				"x" : 1180.0,
				"y" : 1275.0
			},
			"id" : 107,
			"state" : 2
		}
	],
	"time_ns" : 1705575021372353831,
	"trackable" : 1
},
{
	"detections" : 
	[
		{
			"bbox" : 
			{
				"height" : 20.0,
				"width" : 20.0,
				"x" : 1188.0,
				"y" : 1279.0
			},
			"id" : 107,
			"state" : 2
		}
	],
	"time_ns" : 1705575021413560909,
	"trackable" : 1
},
{
	"detections" : 
	[
		{
			"bbox" : 
			{
				"height" : 21.0,
				"width" : 20.0,
				"x" : 1196.0,
				"y" : 1280.0
			},
			"id" : 107,
			"state" : 2
		}
	],
	"time_ns" : 1705575021454345374,
	"trackable" : 1
},
{
	"detections" : 
	[
		{
			"bbox" : 
			{
				"height" : 21.0,
				"width" : 20.0,
				"x" : 1205.0,
				"y" : 1283.0
			},
			"id" : 107,
			"state" : 2
		}
	],
	"time_ns" : 1705575021494171692,
	"trackable" : 1
},
{
	"detections" : 
	[
		{
			"bbox" : 
			{
				"height" : 21.0,
				"width" : 19.0,
				"x" : 1212.0,
				"y" : 1285.0
			},
			"id" : 107,
			"state" : 2
		}
	],
	"time_ns" : 1705575021535581858,
	"trackable" : 1
},
{
	"detections" : 
	[
		{
			"bbox" : 
			{
				"height" : 20.0,
				"width" : 19.0,
				"x" : 1220.0,
				"y" : 1289.0
			},
			"id" : 107,
			"state" : 2
		}
	],
	"time_ns" : 1705575021575866412,
	"trackable" : 1
},
{
	"detections" : 
	[
		{
			"bbox" : 
			{
				"height" : 19.0,
				"width" : 18.0,
				"x" : 1229.0,
				"y" : 1291.0
			},
			"id" : 107,
			"state" : 2
		}
	],
	"time_ns" : 1705575021611484288,
	"trackable" : 1
},
{
	"detections" : 
	[
		{
			"bbox" : 
			{
				"height" : 20.0,
				"width" : 20.0,
				"x" : 1237.0,
				"y" : 1293.0
			},
			"id" : 107,
			"state" : 2
		}
	],
	"time_ns" : 1705575021658377023,
	"trackable" : 1
},
{
	"detections" : 
	[
		{
			"bbox" : 
			{
				"height" : 18.0,
				"width" : 20.0,
				"x" : 1245.0,
				"y" : 1296.0
			},
			"id" : 107,
			"state" : 2
		}
	],
	"time_ns" : 1705575021697562669,
	"trackable" : 1
},
{
	"detections" : 
	[
		{
			"bbox" : 
			{
				"height" : 17.0,
				"width" : 21.0,
				"x" : 1253.0,
				"y" : 1298.0
			},
			"id" : 107,
			"state" : 2
		}
	],
	"time_ns" : 1705575021734435809,
	"trackable" : 1
},
{
	"detections" : 
	[
		{
			"bbox" : 
			{
				"height" : 18.0,
				"width" : 22.0,
				"x" : 1262.0,
				"y" : 1302.0
			},
			"id" : 107,
			"state" : 2
		}
	],
	"time_ns" : 1705575021771279686,
	"trackable" : 1
},
{
	"detections" : 
	[
		{
			"bbox" : 
			{
				"height" : 17.0,
				"width" : 21.0,
				"x" : 1269.0,
				"y" : 1304.0
			},
			"id" : 107,
			"state" : 2
		}
	],
	"time_ns" : 1705575021811211769,
	"trackable" : 1
},
{
	"detections" : 
	[
		{
			"bbox" : 
			{
				"height" : 16.0,
				"width" : 20.0,
				"x" : 1277.0,
				"y" : 1307.0
			},
			"id" : 107,
			"state" : 2
		}
	],
	"time_ns" : 1705575021851247504,
	"trackable" : 1
},
{
	"detections" : 
	[
		{
			"bbox" : 
			{
				"height" : 16.0,
				"width" : 22.0,
				"x" : 1285.0,
				"y" : 1310.0
			},
			"id" : 107,
			"state" : 2
		}
	],
	"time_ns" : 1705575021891798041,
	"trackable" : 1
},
{
	"detections" : 
	[
		{
			"bbox" : 
			{
				"height" : 16.0,
				"width" : 21.0,
				"x" : 1293.0,
				"y" : 1312.0
			},
			"id" : 107,
			"state" : 2
		}
	],
	"time_ns" : 1705575021931577048,
	"trackable" : 1
},
{
	"detections" : 
	[
		{
			"bbox" : 
			{
				"height" : 15.0,
				"width" : 23.0,
				"x" : 1300.0,
				"y" : 1314.0
			},
			"id" : 107,
			"state" : 2
		}
	],
	"time_ns" : 1705575021971122438,
	"trackable" : 1
},
{
	"detections" : 
	[
		{
			"bbox" : 
			{
				"height" : 18.0,
				"width" : 21.0,
				"x" : 1308.0,
				"y" : 1317.0
			},
			"id" : 107,
			"state" : 2
		}
	],
	"time_ns" : 1705575022011773853,
	"trackable" : 1
},
{
	"detections" : 
	[
		{
			"bbox" : 
			{
				"height" : 17.0,
				"width" : 21.0,
				"x" : 1316.0,
				"y" : 1319.0
			},
			"id" : 107,
			"state" : 2
		}
	],
	"time_ns" : 1705575022051932688,
	"trackable" : 1
},
{
	"detections" : 
	[
		{
			"bbox" : 
			{
				"height" : 15.0,
				"width" : 22.0,
				"x" : 1325.0,
				"y" : 1322.0
			},
			"id" : 107,
			"state" : 2
		}
	],
	"time_ns" : 1705575022091909419,
	"trackable" : 1
},
{
	"detections" : 
	[
		{
			"bbox" : 
			{
				"height" : 16.0,
				"width" : 22.0,
				"x" : 1332.0,
				"y" : 1324.0
			},
			"id" : 107,
			"state" : 2
		}
	],
	"time_ns" : 1705575022131497488,
	"trackable" : 1
},
{
	"detections" : 
	[
		{
			"bbox" : 
			{
				"height" : 15.0,
				"width" : 22.0,
				"x" : 1340.0,
				"y" : 1327.0
			},
			"id" : 107,
			"state" : 2
		}
	],
	"time_ns" : 1705575022171878810,
	"trackable" : 1
},
{
	"detections" : 
	[
		{
			"bbox" : 
			{
				"height" : 16.0,
				"width" : 21.0,
				"x" : 1348.0,
				"y" : 1330.0
			},
			"id" : 107,
			"state" : 2
		}
	],
	"time_ns" : 1705575022212189548,
	"trackable" : 1
},
{
	"detections" : 
	[
		{
			"bbox" : 
			{
				"height" : 16.0,
				"width" : 21.0,
				"x" : 1355.0,
				"y" : 1333.0
			},
			"id" : 107,
			"state" : 2
		}
	],
	"time_ns" : 1705575022252621953,
	"trackable" : 1
},
{
	"detections" : 
	[
		{
			"bbox" : 
			{
				"height" : 15.0,
				"width" : 22.0,
				"x" : 1363.0,
				"y" : 1335.0
			},
			"id" : 107,
			"state" : 2
		}
	],
	"time_ns" : 1705575022292454013,
	"trackable" : 1
},
{
	"detections" : 
	[
		{
			"bbox" : 
			{
				"height" : 14.0,
				"width" : 21.0,
				"x" : 1370.0,
				"y" : 1339.0
			},
			"id" : 107,
			"state" : 2
		}
	],
	"time_ns" : 1705575022332691652,
	"trackable" : 1
},
{
	"detections" : 
	[
		{
			"bbox" : 
			{
				"height" : 15.0,
				"width" : 21.0,
				"x" : 1377.0,
				"y" : 1342.0
			},
			"id" : 107,
			"state" : 2
		}
	],
	"time_ns" : 1705575022372394835,
	"trackable" : 1
},
{
	"detections" : 
	[
		{
			"bbox" : 
			{
				"height" : 14.0,
				"width" : 21.0,
				"x" : 1385.0,
				"y" : 1345.0
			},
			"id" : 107,
			"state" : 2
		}
	],
	"time_ns" : 1705575022413609289,
	"trackable" : 1
},
{
	"detections" : 
	[
		{
			"bbox" : 
			{
				"height" : 15.0,
				"width" : 20.0,
				"x" : 1394.0,
				"y" : 1347.0
			},
			"id" : 107,
			"state" : 2
		}
	],
	"time_ns" : 1705575022456506185,
	"trackable" : 1
},
{
	"detections" : 
	[
		{
			"bbox" : 
			{
				"height" : 15.0,
				"width" : 20.0,
				"x" : 1402.0,
				"y" : 1350.0
			},
			"id" : 107,
			"state" : 2
		}
	],
	"time_ns" : 1705575022494725430,
	"trackable" : 1
},
{
	"detections" : 
	[
		{
			"bbox" : 
			{
				"height" : 14.0,
				"width" : 20.0,
				"x" : 1409.0,
				"y" : 1353.0
			},
			"id" : 107,
			"state" : 2
		}
	],
	"time_ns" : 1705575022534716538,
	"trackable" : 1
},
{
	"detections" : 
	[
		{
			"bbox" : 
			{
				"height" : 15.0,
				"width" : 20.0,
				"x" : 1416.0,
				"y" : 1356.0
			},
			"id" : 107,
			"state" : 2
		}
	],
	"time_ns" : 1705575022575706926,
	"trackable" : 1
},
{
	"detections" : 
	[
		{
			"bbox" : 
			{
				"height" : 14.0,
				"width" : 21.0,
				"x" : 1423.0,
				"y" : 1360.0
			},
			"id" : 107,
			"state" : 2
		}
	],
	"time_ns" : 1705575022614791273,
	"trackable" : 1
},
{
	"detections" : 
	[
		{
			"bbox" : 
			{
				"height" : 15.0,
				"width" : 21.0,
				"x" : 1431.0,
				"y" : 1361.0
			},
			"id" : 107,
			"state" : 2
		}
	],
	"time_ns" : 1705575022652783148,
	"trackable" : 1
},
{
	"detections" : 
	[
		{
			"bbox" : 
			{
				"height" : 15.0,
				"width" : 20.0,
				"x" : 1440.0,
				"y" : 1364.0
			},
			"id" : 107,
			"state" : 2
		}
	],
	"time_ns" : 1705575022693250845,
	"trackable" : 1
},
{
	"detections" : 
	[
		{
			"bbox" : 
			{
				"height" : 16.0,
				"width" : 20.0,
				"x" : 1448.0,
				"y" : 1368.0
			},
			"id" : 107,
			"state" : 2
		}
	],
	"time_ns" : 1705575022734698818,
	"trackable" : 1
},
{
	"detections" : 
	[
		{
			"bbox" : 
			{
				"height" : 16.0,
				"width" : 20.0,
				"x" : 1456.0,
				"y" : 1372.0
			},
			"id" : 107,
			"state" : 2
		}
	],
	"time_ns" : 1705575022772982439,
	"trackable" : 1
},
{
	"detections" : 
	[
		{
			"bbox" : 
			{
				"height" : 16.0,
				"width" : 20.0,
				"x" : 1463.0,
				"y" : 1375.0
			},
			"id" : 107,
			"state" : 2
		}
	],
	"time_ns" : 1705575022815108684,
	"trackable" : 1
},
{
	"detections" : 
	[
		{
			"bbox" : 
			{
				"height" : 16.0,
				"width" : 18.0,
				"x" : 1470.0,
				"y" : 1378.0
			},
			"id" : 107,
			"state" : 2
		}
	],
	"time_ns" : 1705575022854537525,
	"trackable" : 1
},
{
	"detections" : 
	[
		{
			"bbox" : 
			{
				"height" : 16.0,
				"width" : 19.0,
				"x" : 1478.0,
				"y" : 1381.0
			},
			"id" : 107,
			"state" : 2
		}
	],
	"time_ns" : 1705575022894290377,
	"trackable" : 1
},
{
	"detections" : 
	[
		{
			"bbox" : 
			{
				"height" : 16.0,
				"width" : 19.0,
				"x" : 1486.0,
				"y" : 1384.0
			},
			"id" : 107,
			"state" : 2
		}
	],
	"time_ns" : 1705575022934952105,
	"trackable" : 1
},
{
	"detections" : 
	[
		{
			"bbox" : 
			{
				"height" : 15.0,
				"width" : 18.0,
				"x" : 1494.0,
				"y" : 1386.0
			},
			"id" : 107,
			"state" : 2
		}
	],
	"time_ns" : 1705575022974951420,
	"trackable" : 1
},
{
	"detections" : 
	[
		{
			"bbox" : 
			{
				"height" : 16.0,
				"width" : 18.0,
				"x" : 1502.0,
				"y" : 1390.0
			},
			"id" : 107,
			"state" : 2
		}
	],
	"time_ns" : 1705575023013876539,
	"trackable" : 1
},
{
	"detections" : 
	[
		{
			"bbox" : 
			{
				"height" : 16.0,
				"width" : 18.0,
				"x" : 1510.0,
				"y" : 1393.0
			},
			"id" : 107,
			"state" : 2
		}
	],
	"time_ns" : 1705575023054606633,
	"trackable" : 1
},
{
	"detections" : 
	[
		{
			"bbox" : 
			{
				"height" : 17.0,
				"width" : 18.0,
				"x" : 1518.0,
				"y" : 1395.0
			},
			"id" : 107,
			"state" : 2
		}
	],
	"time_ns" : 1705575023094233824,
	"trackable" : 1
},
{
	"detections" : 
	[
		{
			"bbox" : 
			{
				"height" : 17.0,
				"width" : 19.0,
				"x" : 1525.0,
				"y" : 1399.0
			},
			"id" : 107,
			"state" : 2
		}
	],
	"time_ns" : 1705575023135051584,
	"trackable" : 1
},
{
	"detections" : 
	[
		{
			"bbox" : 
			{
				"height" : 18.0,
				"width" : 18.0,
				"x" : 1533.0,
				"y" : 1402.0
			},
			"id" : 107,
			"state" : 2
		}
	],
	"time_ns" : 1705575023175121003,
	"trackable" : 1
},
{
	"detections" : 
	[
		{
			"bbox" : 
			{
				"height" : 18.0,
				"width" : 20.0,
				"x" : 1541.0,
				"y" : 1405.0
			},
			"id" : 107,
			"state" : 2
		}
	],
	"time_ns" : 1705575023215799203,
	"trackable" : 1
},
{
	"detections" : 
	[
		{
			"bbox" : 
			{
				"height" : 19.0,
				"width" : 20.0,
				"x" : 1549.0,
				"y" : 1408.0
			},
			"id" : 107,
			"state" : 2
		}
	],
	"time_ns" : 1705575023255055693,
	"trackable" : 1
},
{
	"detections" : 
	[
		{
			"bbox" : 
			{
				"height" : 19.0,
				"width" : 19.0,
				"x" : 1557.0,
				"y" : 1411.0
			},
			"id" : 107,
			"state" : 2
		}
	],
	"time_ns" : 1705575023295665702,
	"trackable" : 1
},
{
	"detections" : 
	[
		{
			"bbox" : 
			{
				"height" : 20.0,
				"width" : 19.0,
				"x" : 1565.0,
				"y" : 1414.0
			},
			"id" : 107,
			"state" : 2
		}
	],
	"time_ns" : 1705575023334388902,
	"trackable" : 1
},
{
	"detections" : 
	[
		{
			"bbox" : 
			{
				"height" : 19.0,
				"width" : 19.0,
				"x" : 1572.0,
				"y" : 1416.0
			},
			"id" : 107,
			"state" : 2
		}
	],
	"time_ns" : 1705575023374634080,
	"trackable" : 1
},
{
	"detections" : 
	[
		{
			"bbox" : 
			{
				"height" : 20.0,
				"width" : 19.0,
				"x" : 1580.0,
				"y" : 1420.0
			},
			"id" : 107,
			"state" : 2
		}
	],
	"time_ns" : 1705575023414966381,
	"trackable" : 1
},
{
	"detections" : 
	[
		{
			"bbox" : 
			{
				"height" : 21.0,
				"width" : 19.0,
				"x" : 1593.0,
				"y" : 1424.0
			},
			"id" : 107,
			"state" : 2
		}
	],
	"time_ns" : 1705575023496411798,
	"trackable" : 1
},
{
	"detections" : 
	[
		{
			"bbox" : 
			{
				"height" : 19.0,
				"width" : 20.0,
				"x" : 1604.0,
				"y" : 1427.0
			},
			"id" : 107,
			"state" : 2
		}
	],
	"time_ns" : 1705575023535621344,
	"trackable" : 1
},
{
	"detections" : 
	[
		{
			"bbox" : 
			{
				"height" : 18.0,
				"width" : 18.0,
				"x" : 1613.0,
				"y" : 1430.0
			},
			"id" : 107,
			"state" : 2
		}
	],
	"time_ns" : 1705575023575614122,
	"trackable" : 1
},
{
	"detections" : 
	[
		{
			"bbox" : 
			{
				"height" : 15.0,
				"width" : 18.0,
				"x" : 1621.0,
				"y" : 1432.0
			},
			"id" : 107,
			"state" : 2
		}
	],
	"time_ns" : 1705575023614913456,
	"trackable" : 1
},
{
	"detections" : 
	[
		{
			"bbox" : 
			{
				"height" : 12.0,
				"width" : 18.0,
				"x" : 1629.0,
				"y" : 1434.0
			},
			"id" : 107,
			"state" : 2
		}
	],
	"time_ns" : 1705575023658214538,
	"trackable" : 1
},
{
	"detections" : 
	[
		{
			"bbox" : 
			{
				"height" : 9.0,
				"width" : 17.0,
				"x" : 1636.0,
				"y" : 1435.0
			},
			"id" : 107,
			"state" : 2
		}
	],
	"time_ns" : 1705575023699440942,
	"trackable" : 1
},
{
	"detections" : 
	[
		{
			"bbox" : 
			{
				"height" : 4.0,
				"width" : 12.0,
				"x" : 1655.0,
				"y" : 1438.0
			},
			"id" : 107,
			"state" : 2
		}
	],
	"time_ns" : 1705575023778692599,
	"trackable" : 1
},
{
	"detections" : 
	[
		{
			"bbox" : 
			{
				"height" : 8.0,
				"width" : 10.0,
				"x" : 1664.0,
				"y" : 1440.0
			},
			"id" : 107,
			"state" : 2
		}
	],
	"time_ns" : 1705575023817470173,
	"trackable" : 1
},
{
	"detections" : 
	[
		{
			"bbox" : 
			{
				"height" : 12.0,
				"width" : 9.0,
				"x" : 1673.0,
				"y" : 1442.0
			},
			"id" : 107,
			"state" : 3
		}
	],
	"time_ns" : 1705575023857422851,
	"trackable" : 0
},
{
	"detections" : 
	[
		{
			"bbox" : 
			{
				"height" : 16.0,
				"width" : 8.0,
				"x" : 1682.0,
				"y" : 1445.0
			},
			"id" : 107,
			"state" : 3
		}
	],
	"time_ns" : 1705575023897234492,
	"trackable" : 0
},
{
	"detections" : 
	[
		{
			"bbox" : 
			{
				"height" : 20.0,
				"width" : 6.0,
				"x" : 1691.0,
				"y" : 1447.0
			},
			"id" : 107,
			"state" : 3
		}
	],
	"time_ns" : 1705575023939424464,
	"trackable" : 0
},
{
	"detections" : 
	[
		{
			"bbox" : 
			{
				"height" : 25.0,
				"width" : 5.0,
				"x" : 1699.0,
				"y" : 1449.0
			},
			"id" : 107,
			"state" : 3
		}
	],
	"time_ns" : 1705575023978666063,
	"trackable" : 0
},
{
	"detections" : 
	[
		{
			"bbox" : 
			{
				"height" : 29.0,
				"width" : 3.0,
				"x" : 1708.0,
				"y" : 1452.0
			},
			"id" : 107,
			"state" : 3
		}
	],
	"time_ns" : 1705575024017313817,
	"trackable" : 0
},
{
	"detections" : 
	[
		{
			"bbox" : 
			{
				"height" : 33.0,
				"width" : 2.0,
				"x" : 1717.0,
				"y" : 1454.0
			},
			"id" : 107,
			"state" : 3
		}
	],
	"time_ns" : 1705575024057806738,
	"trackable" : 0
},
{
	"detections" : 
	[
		{
			"bbox" : 
			{
				"height" : 37.0,
				"width" : 0.0,
				"x" : 1726.0,
				"y" : 1456.0
			},
			"id" : 107,
			"state" : 3
		}
	],
	"time_ns" : 1705575024097251905,
	"trackable" : 0
},
{
	"detections" : 
	[
		{
			"bbox" : 
			{
				"height" : 41.0,
				"width" : 0.0,
				"x" : 1735.0,
				"y" : 1459.0
			},
			"id" : 107,
			"state" : 3
		}
	],
	"time_ns" : 1705575024136523598,
	"trackable" : 0
},
{
	"detections" : 
	[
		{
			"bbox" : 
			{
				"height" : 45.0,
				"width" : 0.0,
				"x" : 1744.0,
				"y" : 1461.0
			},
			"id" : 107,
			"state" : 3
		}
	],
	"time_ns" : 1705575024178765035,
	"trackable" : 0
},
{
	"detections" : 
	[
		{
			"bbox" : 
			{
				"height" : 49.0,
				"width" : 0.0,
				"x" : 1753.0,
				"y" : 1464.0
			},
			"id" : 107,
			"state" : 3
		}
	],
	"time_ns" : 1705575024218109706,
	"trackable" : 0
},
{
	"detections" : 
	[
		{
			"bbox" : 
			{
				"height" : 54.0,
				"width" : 0.0,
				"x" : 1762.0,
				"y" : 1467.0
			},
			"id" : 107,
			"state" : 3
		}
	],
	"time_ns" : 1705575024256814109,
	"trackable" : 0
},
{
	"detections" : 
	[
		{
			"bbox" : 
			{
				"height" : 58.0,
				"width" : 0.0,
				"x" : 1770.0,
				"y" : 1469.0
			},
			"id" : 107,
			"state" : 3
		}
	],
	"time_ns" : 1705575024296746233,
	"trackable" : 0
},
{
	"detections" : 
	[
		{
			"bbox" : 
			{
				"height" : 62.0,
				"width" : 0.0,
				"x" : 1779.0,
				"y" : 1471.0
			},
			"id" : 107,
			"state" : 3
		}
	],
	"time_ns" : 1705575024338514255,
	"trackable" : 0
},
{
	"detections" : 
	[
		{
			"bbox" : 
			{
				"height" : 66.0,
				"width" : 0.0,
				"x" : 1788.0,
				"y" : 1474.0
			},
			"id" : 107,
			"state" : 3
		}
	],
	"time_ns" : 1705575024377806018,
	"trackable" : 0
},
{
	"detections" : 
	[
		{
			"bbox" : 
			{
				"height" : 70.0,
				"width" : 0.0,
				"x" : 1797.0,
				"y" : 1476.0
			},
			"id" : 107,
			"state" : 3
		}
	],
	"time_ns" : 1705575024416774425,
	"trackable" : 0
},
{
	"detections" : 
	[
		{
			"bbox" : 
			{
				"height" : 74.0,
				"width" : 0.0,
				"x" : 1806.0,
				"y" : 1479.0
			},
			"id" : 107,
			"state" : 3
		}
	],
	"time_ns" : 1705575024457170834,
	"trackable" : 0
},
{
	"detections" : 
	[
		{
			"bbox" : 
			{
				"height" : 78.0,
				"width" : 0.0,
				"x" : 1815.0,
				"y" : 1481.0
			},
			"id" : 107,
			"state" : 3
		}
	],
	"time_ns" : 1705575024498431784,
	"trackable" : 0
},
{
	"detections" : 
	[
		{
			"bbox" : 
			{
				"height" : 82.0,
				"width" : 0.0,
				"x" : 1823.0,
				"y" : 1484.0
			},
			"id" : 107,
			"state" : 3
		}
	],
	"time_ns" : 1705575024538970807,
	"trackable" : 0
},
{
	"detections" : 
	[
		{
			"bbox" : 
			{
				"height" : 87.0,
				"width" : 0.0,
				"x" : 1832.0,
				"y" : 1485.0
			},
			"id" : 107,
			"state" : 3
		}
	],
	"time_ns" : 1705575024578766169,
	"trackable" : 0
},
{
	"detections" : 
	[
		{
			"bbox" : 
			{
				"height" : 91.0,
				"width" : 0.0,
				"x" : 1841.0,
				"y" : 1488.0
			},
			"id" : 107,
			"state" : 3
		}
	],
	"time_ns" : 1705575024618826813,
	"trackable" : 0
},
{
	"detections" : 
	[
		{
			"bbox" : 
			{
				"height" : 95.0,
				"width" : 0.0,
				"x" : 1850.0,
				"y" : 1490.0
			},
			"id" : 107,
			"state" : 3
		}
	],
	"time_ns" : 1705575024659810020,
	"trackable" : 0
},
{
	"detections" : 
	[
		{
			"bbox" : 
			{
				"height" : 99.0,
				"width" : 0.0,
				"x" : 1859.0,
				"y" : 1493.0
			},
			"id" : 107,
			"state" : 3
		}
	],
	"time_ns" : 1705575024699069143,
	"trackable" : 0
},
{
	"detections" : 
	[
		{
			"bbox" : 
			{
				"height" : 103.0,
				"width" : 0.0,
				"x" : 1868.0,
				"y" : 1495.0
			},
			"id" : 107,
			"state" : 3
		}
	],
	"time_ns" : 1705575024738532786,
	"trackable" : 0
},
{
	"detections" : 
	[
		{
			"bbox" : 
			{
				"height" : 107.0,
				"width" : 0.0,
				"x" : 1877.0,
				"y" : 1498.0
			},
			"id" : 107,
			"state" : 3
		}
	],
	"time_ns" : 1705575024777782168,
	"trackable" : 0
},
{
	"detections" : 
	[
		{
			"bbox" : 
			{
				"height" : 111.0,
				"width" : 0.0,
				"x" : 1885.0,
				"y" : 1500.0
			},
			"id" : 107,
			"state" : 3
		}
	],
	"time_ns" : 1705575024817880506,
	"trackable" : 0
},
{
	"detections" : 
	[
		{
			"bbox" : 
			{
				"height" : 115.0,
				"width" : 0.0,
				"x" : 1894.0,
				"y" : 1502.0
			},
			"id" : 107,
			"state" : 3
		}
	],
	"time_ns" : 1705575024858305470,
	"trackable" : 0
},
{
	"detections" : 
	[
		{
			"bbox" : 
			{
				"height" : 120.0,
				"width" : 0.0,
				"x" : 1903.0,
				"y" : 1505.0
			},
			"id" : 107,
			"state" : 3
		}
	],
	"time_ns" : 1705575024899095119,
	"trackable" : 0
},
{
	"detections" : 
	[
		{
			"bbox" : 
			{
				"height" : 124.0,
				"width" : 0.0,
				"x" : 1912.0,
				"y" : 1508.0
			},
			"id" : 107,
			"state" : 3
		}
	],
	"time_ns" : 1705575024941001370,
	"trackable" : 0
},
{
	"detections" : 
	[
		{
			"bbox" : 
			{
				"height" : 128.0,
				"width" : 0.0,
				"x" : 1921.0,
				"y" : 1510.0
			},
			"id" : 107,
			"state" : 3
		}
	],
	"time_ns" : 1705575024980039376,
	"trackable" : 0
},
{
	"detections" : 
	[
		{
			"bbox" : 
			{
				"height" : 132.0,
				"width" : 0.0,
				"x" : 1930.0,
				"y" : 1513.0
			},
			"id" : 107,
			"state" : 3
		}
	],
	"time_ns" : 1705575025020668811,
	"trackable" : 0
},
{
	"detections" : 
	[
		{
			"bbox" : 
			{
				"height" : 136.0,
				"width" : 0.0,
				"x" : 1938.0,
				"y" : 1515.0
			},
			"id" : 107,
			"state" : 3
		}
	],
	"time_ns" : 1705575025059192197,
	"trackable" : 0
},
{
	"detections" : 
	[
		{
			"bbox" : 
			{
				"height" : 140.0,
				"width" : 0.0,
				"x" : 1947.0,
				"y" : 1517.0
			},
			"id" : 107,
			"state" : 3
		}
	],
	"time_ns" : 1705575025101161958,
	"trackable" : 0
},
{
	"detections" : 
	[
		{
			"bbox" : 
			{
				"height" : 144.0,
				"width" : 0.0,
				"x" : 1956.0,
				"y" : 1520.0
			},
			"id" : 107,
			"state" : 3
		}
	],
	"time_ns" : 1705575025139840938,
	"trackable" : 0
},
{
	"detections" : 
	[
		{
			"bbox" : 
			{
				"height" : 148.0,
				"width" : 0.0,
				"x" : 1965.0,
				"y" : 1522.0
			},
			"id" : 107,
			"state" : 3
		}
	],
	"time_ns" : 1705575025180286486,
	"trackable" : 0
},
{
	"detections" : 
	[
		{
			"bbox" : 
			{
				"height" : 153.0,
				"width" : 0.0,
				"x" : 1974.0,
				"y" : 1524.0
			},
			"id" : 107,
			"state" : 3
		}
	],
	"time_ns" : 1705575025219921044,
	"trackable" : 0
},
{
	"detections" : 
	[
		{
			"bbox" : 
			{
				"height" : 157.0,
				"width" : 0.0,
				"x" : 1983.0,
				"y" : 1527.0
			},
			"id" : 107,
			"state" : 3
		}
	],
	"time_ns" : 1705575025258528615,
	"trackable" : 0
},
{
	"detections" : 
	[
		{
			"bbox" : 
			{
				"height" : 161.0,
				"width" : 0.0,
				"x" : 1992.0,
				"y" : 1529.0
			},
			"id" : 107,
			"state" : 3
		}
	],
	"time_ns" : 1705575025299192862,
	"trackable" : 0
},
{
	"detections" : 
	[
		{
			"bbox" : 
			{
				"height" : 165.0,
				"width" : 0.0,
				"x" : 2000.0,
				"y" : 1531.0
			},
			"id" : 107,
			"state" : 3
		}
	],
	"time_ns" : 1705575025419936152,
	"trackable" : 0
},
{
	"detections" : 
	[
		{
			"bbox" : 
			{
				"height" : 169.0,
				"width" : 0.0,
				"x" : 2009.0,
				"y" : 1534.0
			},
			"id" : 107,
			"state" : 3
		}
	],
	"time_ns" : 1705575025460211593,
	"trackable" : 0
},
{
	"detections" : 
	[
		{
			"bbox" : 
			{
				"height" : 173.0,
				"width" : 0.0,
				"x" : 2018.0,
				"y" : 1536.0
			},
			"id" : 107,
			"state" : 3
		}
	],
	"time_ns" : 1705575025498613036,
	"trackable" : 0
},
{
	"detections" : 
	[
		{
			"bbox" : 
			{
				"height" : 177.0,
				"width" : 0.0,
				"x" : 2027.0,
				"y" : 1539.0
			},
			"id" : 107,
			"state" : 3
		}
	],
	"time_ns" : 1705575025540069801,
	"trackable" : 0
},
{
	"detections" : 
	[
		{
			"bbox" : 
			{
				"height" : 181.0,
				"width" : 0.0,
				"x" : 2036.0,
				"y" : 1541.0
			},
			"id" : 107,
			"state" : 3
		}
	],
	"time_ns" : 1705575025581764566,
	"trackable" : 0
},
{
	"detections" : 
	[
		{
			"bbox" : 
			{
				"height" : 186.0,
				"width" : 0.0,
				"x" : 2045.0,
				"y" : 1544.0
			},
			"id" : 107,
			"state" : 3
		}
	],
	"time_ns" : 1705575025622574029,
	"trackable" : 0
},
{
	"detections" : 
	[
		{
			"bbox" : 
			{
				"height" : 190.0,
				"width" : 0.0,
				"x" : 2053.0,
				"y" : 1546.0
			},
			"id" : 107,
			"state" : 3
		}
	],
	"time_ns" : 1705575025664052372,
	"trackable" : 0
},
{
	"detections" : null,
	"time_ns" : 1705575025705054987,
	"trackable" : 0
},
{
	"detections" : null,
	"time_ns" : 1705575025742360907,
	"trackable" : 0
},
{
	"detections" : null,
	"time_ns" : 1705575025821162866,
	"trackable" : 0
},
{
	"detections" : null,
	"time_ns" : 1705575025865316697,
	"trackable" : 0
},
{
	"detections" : null,
	"time_ns" : 1705575025904280063,
	"trackable" : 0
},
{
	"detections" : null,
	"time_ns" : 1705575025943928862,
	"trackable" : 0
},
{
	"detections" : null,
	"time_ns" : 1705575025980593426,
	"trackable" : 0
}]
